fsdviewer/__init__.py
fsdviewer/viewer2d.py
fsd_viewer_jpvolt-0.0.7.dist-info/LICENSE
fsd_viewer_jpvolt-0.0.7.dist-info/METADATA
fsd_viewer_jpvolt-0.0.7.dist-info/WHEEL
fsd_viewer_jpvolt-0.0.7.dist-info/top_level.txt
fsd_viewer_jpvolt-0.0.7.dist-info/RECORD
