Metadata-Version: 2.1
Name: fsd-viewer-jpvolt
Version: 0.0.7
Summary: Simple 2d viewer for formula student driverless projects
Home-page: https://github.com/jpvolt/fsdviewer
Author: João Voltani
Author-email: jpvoltdeveloper@gmail.com
License: UNKNOWN
Platform: UNKNOWN
Classifier: Programming Language :: Python :: 3
Classifier: License :: OSI Approved :: MIT License
Classifier: Operating System :: OS Independent
Requires-Python: >=3.6
